mpmaps/__init__.py
mpmaps/globals.py
mpmaps/mpmaps.py
mpmaps-0.2.0.dist-info/LICENSE
mpmaps-0.2.0.dist-info/WHEEL
mpmaps-0.2.0.dist-info/METADATA
mpmaps-0.2.0.dist-info/RECORD
